{"name":"Lastchat","tagline":"chatroom","body":"Demo\r\n----\r\n\r\n[http://talk-here.appspot.com](http://talk-here.appspot.com)\r\n\r\nAbout\r\n-----\r\n\r\n`lastchat` is a chatroom engine designed to run on Google App Engine.\r\n\r\n\r\n1. It is designed as a public chatroom that requires only one username (YES, no anonying registration and the username doesn't have to be unique!)\r\n2. Everything here is designed to be public, your username, your message\r\n3. Fun features coming. such as `THE HOLE`. [More](https://github.com/lastr2d2/lastchat/wiki/THE-HOLE)\r\n\r\nTechnology\r\n----------\r\n\r\n1.  web.py as the web framework. [More](http://webpy.org/)\r\n2.  Bootstrap as front-end web framework. [More](getbootstrap.com)\r\n\r\n3.  Google App Engine \r\n    1. Channel to create a persistent connection between your application and Google servers. [More](https://developers.google.com/appengine/docs/python/channel/)\r\n    2. Memcache to store connections [More](https://developers.google.com/appengine/docs/python/memcache/)\r\n  \r\n4.  jQuery, of course. [More](http://jquery.com/)\r\n\r\n5.  jQuery plugins\r\n    1.  jQuery.timeago, a plugin to automatically update fuzzy timestamps. [More](https://github.com/rmm5t/jquery-timeago)\r\n    2.  jQuery.cookie, for reading, writing and deleting cookies. [More](https://github.com/carhartl/jquery-cookie)\r\n","google":"","note":"Don't delete this file! It's used internally to help with page regeneration."}